secureproximity/__init__.py
secureproximity/cli.py
secureproximity/config.py
secureproximity/core.py
secureproximity/utils.py
secureproximity-1.1.0.dist-info/licenses/LICENSE
secureproximity-1.1.0.dist-info/METADATA
secureproximity-1.1.0.dist-info/WHEEL
secureproximity-1.1.0.dist-info/entry_points.txt
secureproximity-1.1.0.dist-info/top_level.txt
secureproximity-1.1.0.dist-info/RECORD
