Metadata-Version: 2.4
Name: secureproximity
Version: 1.1.0
Summary: Advanced security CLI tool that locks your system when your phone moves out of Bluetooth range.
Home-page: https://github.com/codewithevilxd/SecureProximity
Author: Nishant Gaurav
Author-email: codewithevilxd@gmail.com
Requires-Python: >=3.8
License-File: LICENSE
Requires-Dist: bleak>=0.21.0
Dynamic: author
Dynamic: author-email
Dynamic: description
Dynamic: description-content-type
Dynamic: home-page
Dynamic: license-file
Dynamic: requires-dist
Dynamic: requires-python
Dynamic: summary
